ai_utilities/__init__.py
ai_utilities/ai_config_manager.py
ai_utilities/ai_integration.py
ai_utilities/rate_limiter.py
ai_utilities-0.3.0.dist-info/LICENSE
ai_utilities-0.3.0.dist-info/METADATA
ai_utilities-0.3.0.dist-info/WHEEL
ai_utilities-0.3.0.dist-info/top_level.txt
ai_utilities-0.3.0.dist-info/RECORD
