Metadata-Version: 2.1
Name: ai_utilities
Version: 0.3.0
Summary: Utilities for AI configuration management and integration.
Home-page: https://github.com/audkus/ai_utilities.git
Author: Steffen S. Rasmussen
Author-email: steffen@audkus.dk
License-File: LICENSE
Requires-Dist: openai
Requires-Dist: config-utilities
Requires-Dist: psutil
